_ert/__init__.py
_ert/events.py
_ert/threading.py
_ert/utils.py
_ert/forward_model_runner/__init__.py
_ert/forward_model_runner/client.py
_ert/forward_model_runner/fm_dispatch.py
_ert/forward_model_runner/forward_model_step.py
_ert/forward_model_runner/runner.py
_ert/forward_model_runner/io/__init__.py
_ert/forward_model_runner/reporting/__init__.py
_ert/forward_model_runner/reporting/base.py
_ert/forward_model_runner/reporting/event.py
_ert/forward_model_runner/reporting/file.py
_ert/forward_model_runner/reporting/interactive.py
_ert/forward_model_runner/reporting/message.py
_ert/forward_model_runner/reporting/statemachine.py
_ert/forward_model_runner/util/__init__.py
_ert/forward_model_runner/util/data.py
ert/__init__.py
ert/__main__.py
ert/base_model_context.py
ert/constant_filenames.py
ert/libres_facade.py
ert/mode_definitions.py
ert/namespace.py
ert/run_arg.py
ert/runpaths.py
ert/sample_prior.py
ert/substitutions.py
ert/trace.py
ert/workflow_runner.py
ert/analysis/__init__.py
ert/analysis/_enif_update.py
ert/analysis/_es_update.py
ert/analysis/_update_commons.py
ert/analysis/event.py
ert/analysis/misfit_preprocessor.py
ert/analysis/snapshots.py
ert/cli/__init__.py
ert/cli/main.py
ert/cli/monitor.py
ert/cli/workflow.py
ert/config/__init__.py
ert/config/_create_observation_dataframes.py
ert/config/_design_matrix_validator.py
ert/config/_get_num_cpu.py
ert/config/_observations.py
ert/config/_read_summary.py
ert/config/_str_to_bool.py
ert/config/analysis_config.py
ert/config/analysis_module.py
ert/config/capture_validation.py
ert/config/design_matrix.py
ert/config/distribution.py
ert/config/ensemble_config.py
ert/config/ert_config.py
ert/config/ert_plugin.py
ert/config/ert_script.py
ert/config/everest_response.py
ert/config/ext_param_config.py
ert/config/external_ert_script.py
ert/config/field.py
ert/config/forward_model_step.py
ert/config/gen_data_config.py
ert/config/gen_kw_config.py
ert/config/known_response_types.py
ert/config/lint_file.py
ert-18.0.8.dist-info/licenses/COPYING
ert-18.0.8.dist-info/METADATA
ert-18.0.8.dist-info/WHEEL
ert-18.0.8.dist-info/entry_points.txt
ert-18.0.8.dist-info/top_level.txt
ert-18.0.8.dist-info/RECORD
