Metadata-Version: 2.4
Name: ert
Version: 18.0.8
Summary: Ensemble based Reservoir Tool (ERT)
Author-email: Equinor ASA <fg_sib-scout@equinor.com>
License-Expression: GPL-3.0-only
Project-URL: Repository, https://github.com/equinor/ert
Platform: all
Classifier: Development Status :: 5 - Production/Stable
Classifier: Environment :: Other Environment
Classifier: Intended Audience :: Science/Research
Classifier: Natural Language :: English
Classifier: Programming Language :: Python
Classifier: Programming Language :: Python :: 3.11
Classifier: Programming Language :: Python :: 3.12
Classifier: Programming Language :: Python :: 3.13
Classifier: Topic :: Scientific/Engineering
Classifier: Topic :: Scientific/Engineering :: Physics
Requires-Python: <3.14,>=3.11
License-File: COPYING
Requires-Dist: aiohttp
Requires-Dist: anyio
Requires-Dist: colorama
Requires-Dist: cryptography
Requires-Dist: decorator
Requires-Dist: dnspython>=2
Requires-Dist: fastapi
Requires-Dist: fastexcel>=0.14.0
Requires-Dist: filelock
Requires-Dist: graphite-maps
Requires-Dist: httpx
Requires-Dist: httpx-retries
Requires-Dist: humanize
Requires-Dist: iterative_ensemble_smoother>=0.4.0
Requires-Dist: jinja2>=2.10
Requires-Dist: lark
Requires-Dist: lxml
Requires-Dist: matplotlib
Requires-Dist: netCDF4
Requires-Dist: networkx
Requires-Dist: numpy
Requires-Dist: opentelemetry-api
Requires-Dist: opentelemetry-instrumentation-threading
Requires-Dist: opentelemetry-sdk
Requires-Dist: orjson
Requires-Dist: packaging
Requires-Dist: pandas
Requires-Dist: pluggy>=1.3.0
Requires-Dist: polars<1.35,>=1.32.3
Requires-Dist: progressbar2
Requires-Dist: psutil
Requires-Dist: pyarrow
Requires-Dist: pydantic>2
Requires-Dist: pyqt6<6.10.0
Requires-Dist: python-dateutil
Requires-Dist: python-multipart
Requires-Dist: pyyaml
Requires-Dist: pyzmq
Requires-Dist: requests
Requires-Dist: resfo>=5.0.0
Requires-Dist: ropt-dakota<0.26,>=0.25
Requires-Dist: ropt[pandas]<0.26,>=0.25
Requires-Dist: ruamel.yaml
Requires-Dist: scipy>=1.10.1
Requires-Dist: seaborn
Requires-Dist: surfio>=0.0.11
Requires-Dist: tables
Requires-Dist: tabulate
Requires-Dist: tqdm>=4.62.0
Requires-Dist: typing_extensions>=4.5
Requires-Dist: uvicorn>=0.17.0
Requires-Dist: websockets
Requires-Dist: xarray
Requires-Dist: xtgeo>=3.3.0
Requires-Dist: resfo-utilities>=0.5.0
Provides-Extra: dev
Requires-Dist: furo; extra == "dev"
Requires-Dist: hypothesis!=6.102.0,!=6.112.3,>=6.85; extra == "dev"
Requires-Dist: jsonpath_ng; extra == "dev"
Requires-Dist: jupyter; extra == "dev"
Requires-Dist: jupytext; extra == "dev"
Requires-Dist: nbsphinx; extra == "dev"
Requires-Dist: oil_reservoir_synthesizer; extra == "dev"
Requires-Dist: pytest-asyncio; extra == "dev"
Requires-Dist: pytest-benchmark; extra == "dev"
Requires-Dist: pytest-cov; extra == "dev"
Requires-Dist: pytest-memray; extra == "dev"
Requires-Dist: pytest-mock; extra == "dev"
Requires-Dist: pytest-mpl; extra == "dev"
Requires-Dist: pytest-qt; extra == "dev"
Requires-Dist: pytest-raises; extra == "dev"
Requires-Dist: pytest-rerunfailures!=16.0; extra == "dev"
Requires-Dist: pytest-snapshot; extra == "dev"
Requires-Dist: pytest-timeout; extra == "dev"
Requires-Dist: pytest-xdist; extra == "dev"
Requires-Dist: pytest-durations; extra == "dev"
Requires-Dist: pytest>6; extra == "dev"
Requires-Dist: resdata; extra == "dev"
Requires-Dist: rust-just; extra == "dev"
Requires-Dist: scikit-image; extra == "dev"
Requires-Dist: sphinx; extra == "dev"
Requires-Dist: sphinx-argparse; extra == "dev"
Requires-Dist: sphinx-autoapi; extra == "dev"
Requires-Dist: sphinx-copybutton; extra == "dev"
Requires-Dist: sphinxcontrib.datatemplates; extra == "dev"
Requires-Dist: json-schema-for-humans; extra == "dev"
Requires-Dist: xlsxwriter>=3.2.3; extra == "dev"
Requires-Dist: resfo-utilities[testing]>=0.5.0; extra == "dev"
Provides-Extra: style
Requires-Dist: pre-commit; extra == "style"
Provides-Extra: types
Requires-Dist: mypy; extra == "types"
Requires-Dist: types-lxml; extra == "types"
Requires-Dist: types-requests; extra == "types"
Requires-Dist: types-PyYAML; extra == "types"
Requires-Dist: types-python-dateutil; extra == "types"
Requires-Dist: types-decorator; extra == "types"
Requires-Dist: types-docutils; extra == "types"
Requires-Dist: types-tqdm; extra == "types"
Requires-Dist: types-psutil; extra == "types"
Requires-Dist: types-setuptools; extra == "types"
Requires-Dist: types-networkx; extra == "types"
Dynamic: license-file
